{
  "modelName": "google/gemma-4-e2b",
  "generatedAtUtc": "2026-05-07T22:38:25.2361296Z",
  "verseId": 6,
  "surahNumber": 96,
  "verseNumber": 6,
  "arabicText": "كَلَّآ إِنَّ ٱلْإِنسَٰنَ لَيَطْغَىٰٓ",
  "turkishTranslation": "Ama, insanoğlu kendini müstağni sayarak azgınlık eder.",
  "interpretationTr": "Bu ayet, insanın kendi varlığını ve gücünü aşırı derecede öznel bir şekilde değerlendirmesi sonucu kibirlenerek sınırları aştığını ifade eder. İnsan, kendini bağımsız ve müstağni (kendine yeten) olarak görmeye başladığında, bu durum onun azgınlık ve aşırılığa (yaṭğā) yol açar. Yani, insanın kendi üstünlüğüne dair algısı, onu sınırları zorlamaya iten bir eğilime neden olur."
}
