{
  "SurahEnglishName": "Nooh",
  "SurahNumber": 71,
  "RevelationOrder": 71,
  "Verses": [
    {
      "RevelationOrder": 3804,
      "TurkishTranslation": "\"Milletine can yakıcı bir azap gelmezden önce onları uyar\" diye Nuh'u milletine gönderdik.",
      "ArabicText": "بِسْمِ ٱللَّهِ ٱلرَّحْمَٰنِ ٱلرَّحِيمِ إِنَّآ أَرْسَلْنَا نُوحًا إِلَىٰ قَوْمِهِۦٓ أَنْ أَنذِرْ قَوْمَكَ مِن قَبْلِ أَن يَأْتِيَهُمْ عَذَابٌ أَلِيمٌۭ",
      "Number": 1
    },
    {
      "RevelationOrder": 3805,
      "TurkishTranslation": "O da şöyle söyledi: \"Ey Milletim! Şüphesiz ben, size gönderilmiş apaçık bir uyarıcıyım.\"",
      "ArabicText": "قَالَ يَٰقَوْمِ إِنِّى لَكُمْ نَذِيرٌۭ مُّبِينٌ",
      "Number": 2
    },
    {
      "RevelationOrder": 3806,
      "TurkishTranslation": "\"Allah'a kulluk edin; O'ndan sakının ve bana itaat edin ki Allah günahlarınızı size bağışlasın ve sizi belli bir süreye kadar ertelesin; doğrusu Allah'ın belirttiği süre gelince geri bırakılamaz; keşke bilseniz!\"",
      "ArabicText": "أَنِ ٱعْبُدُوا۟ ٱللَّهَ وَٱتَّقُوهُ وَأَطِيعُونِ",
      "Number": 3
    },
    {
      "RevelationOrder": 3807,
      "TurkishTranslation": "\"Allah'a kulluk edin; O'ndan sakının ve bana itaat edin ki Allah günahlarınızı size bağışlasın ve sizi belli bir süreye kadar ertelesin; doğrusu Allah'ın belirttiği süre gelince geri bırakılamaz; keşke bilseniz!\"",
      "ArabicText": "يَغْفِرْ لَكُم مِّن ذُنُوبِكُمْ وَيُؤَخِّرْكُمْ إِلَىٰٓ أَجَلٍۢ مُّسَمًّى ۚ إِنَّ أَجَلَ ٱللَّهِ إِذَا جَآءَ لَا يُؤَخَّرُ ۖ لَوْ كُنتُمْ تَعْلَمُونَ",
      "Number": 4
    },
    {
      "RevelationOrder": 3808,
      "TurkishTranslation": "Nuh dedi ki: \"Rabbim! Doğrusu ben, milletimi gece gündüz çağırdım.\"",
      "ArabicText": "قَالَ رَبِّ إِنِّى دَعَوْتُ قَوْمِى لَيْلًۭا وَنَهَارًۭا",
      "Number": 5
    },
    {
      "RevelationOrder": 3809,
      "TurkishTranslation": "\"Fakat benim çağırmam, sadece benden uzaklıklarını artırdı.\"",
      "ArabicText": "فَلَمْ يَزِدْهُمْ دُعَآءِىٓ إِلَّا فِرَارًۭا",
      "Number": 6
    },
    {
      "RevelationOrder": 3810,
      "TurkishTranslation": "\"Doğrusu ben Senin onları bağışlaman için kendilerini her çağırışımda, parmaklarını kulaklarına tıkadılar, elbiselerine büründüler, direndiler, büyüklendikçe büyüklendiler.\"",
      "ArabicText": "وَإِنِّى كُلَّمَا دَعَوْتُهُمْ لِتَغْفِرَ لَهُمْ جَعَلُوٓا۟ أَصَٰبِعَهُمْ فِىٓ ءَاذَانِهِمْ وَٱسْتَغْشَوْا۟ ثِيَابَهُمْ وَأَصَرُّوا۟ وَٱسْتَكْبَرُوا۟ ٱسْتِكْبَارًۭا",
      "Number": 7
    },
    {
      "RevelationOrder": 3811,
      "TurkishTranslation": "\"Sonra, doğrusu ben onları açıkça çağırdım.\"",
      "ArabicText": "ثُمَّ إِنِّى دَعَوْتُهُمْ جِهَارًۭا",
      "Number": 8
    },
    {
      "RevelationOrder": 3812,
      "TurkishTranslation": "\"Sonra onlara açıktan açığa, gizliden gizliye de söyledim.\"",
      "ArabicText": "ثُمَّ إِنِّىٓ أَعْلَنتُ لَهُمْ وَأَسْرَرْتُ لَهُمْ إِسْرَارًۭا",
      "Number": 9
    },
    {
      "RevelationOrder": 3813,
      "TurkishTranslation": "Dedim ki: \"Rabbinizden bağışlanma dileyin; doğrusu O, çok bağışlayandır. Size gökten bol bol yağmur indirsin.\"",
      "ArabicText": "فَقُلْتُ ٱسْتَغْفِرُوا۟ رَبَّكُمْ إِنَّهُۥ كَانَ غَفَّارًۭا",
      "Number": 10
    },
    {
      "RevelationOrder": 3814,
      "TurkishTranslation": "Dedim ki: \"Rabbinizden bağışlanma dileyin; doğrusu O, çok bağışlayandır. Size gökten bol bol yağmur indirsin.\"",
      "ArabicText": "يُرْسِلِ ٱلسَّمَآءَ عَلَيْكُم مِّدْرَارًۭا",
      "Number": 11
    },
    {
      "RevelationOrder": 3815,
      "TurkishTranslation": "\"Sizi, mallar ve oğullarla desteklesin; sizin için bahçeler var etsin, ırmaklar akıtsın.\"",
      "ArabicText": "وَيُمْدِدْكُم بِأَمْوَٰلٍۢ وَبَنِينَ وَيَجْعَل لَّكُمْ جَنَّٰتٍۢ وَيَجْعَل لَّكُمْ أَنْهَٰرًۭا",
      "Number": 12
    },
    {
      "RevelationOrder": 3816,
      "TurkishTranslation": "\"Ne oluyorsunuz ki Allah'a büyüklüğü yakıştıramıyorsunuz.\"",
      "ArabicText": "مَّا لَكُمْ لَا تَرْجُونَ لِلَّهِ وَقَارًۭا",
      "Number": 13
    },
    {
      "RevelationOrder": 3817,
      "TurkishTranslation": "\"Oysa sizi merhalelerden geçirerek O yaratmıştır.\"",
      "ArabicText": "وَقَدْ خَلَقَكُمْ أَطْوَارًا",
      "Number": 14
    },
    {
      "RevelationOrder": 3818,
      "TurkishTranslation": "\"Allah'ın, göğü yedi kat üzerine nasıl yarattığını görmez misiniz?\"",
      "ArabicText": "أَلَمْ تَرَوْا۟ كَيْفَ خَلَقَ ٱللَّهُ سَبْعَ سَمَٰوَٰتٍۢ طِبَاقًۭا",
      "Number": 15
    },
    {
      "RevelationOrder": 3819,
      "TurkishTranslation": "\"Aralarında aya aydınlık vermiş ve güneşin ışık saçmasını sağlamıştır.\"",
      "ArabicText": "وَجَعَلَ ٱلْقَمَرَ فِيهِنَّ نُورًۭا وَجَعَلَ ٱلشَّمْسَ سِرَاجًۭا",
      "Number": 16
    },
    {
      "RevelationOrder": 3820,
      "TurkishTranslation": "\"Allah sizi yerden bitirir gibi yetiştirmiştir.\"",
      "ArabicText": "وَٱللَّهُ أَنۢبَتَكُم مِّنَ ٱلْأَرْضِ نَبَاتًۭا",
      "Number": 17
    },
    {
      "RevelationOrder": 3821,
      "TurkishTranslation": "\"Sonra sizi oraya döndürür ve yine oradan çıkarır.\"",
      "ArabicText": "ثُمَّ يُعِيدُكُمْ فِيهَا وَيُخْرِجُكُمْ إِخْرَاجًۭا",
      "Number": 18
    },
    {
      "RevelationOrder": 3822,
      "TurkishTranslation": "\"Yeryüzünde dolaşabilmeniz, orada yollar ve geniş geçitlerden geçebilmeniz için, onu size yayan O'dur.\"",
      "ArabicText": "وَٱللَّهُ جَعَلَ لَكُمُ ٱلْأَرْضَ بِسَاطًۭا",
      "Number": 19
    },
    {
      "RevelationOrder": 3823,
      "TurkishTranslation": "\"Yeryüzünde dolaşabilmeniz, orada yollar ve geniş geçitlerden geçebilmeniz için, onu size yayan O'dur.\"",
      "ArabicText": "لِّتَسْلُكُوا۟ مِنْهَا سُبُلًۭا فِجَاجًۭا",
      "Number": 20
    },
    {
      "RevelationOrder": 3824,
      "TurkishTranslation": "Nuh: \"Rabbim! Doğrusu bunlar bana baş kaldırdılar ve malı, çocuğu kendisine sadece zarar getiren kimseye uydular; birbirinden büyük düzenler kurdular\" dedi.",
      "ArabicText": "قَالَ نُوحٌۭ رَّبِّ إِنَّهُمْ عَصَوْنِى وَٱتَّبَعُوا۟ مَن لَّمْ يَزِدْهُ مَالُهُۥ وَوَلَدُهُۥٓ إِلَّا خَسَارًۭا",
      "Number": 21
    },
    {
      "RevelationOrder": 3825,
      "TurkishTranslation": "Nuh: \"Rabbim! Doğrusu bunlar bana baş kaldırdılar ve malı, çocuğu kendisine sadece zarar getiren kimseye uydular; birbirinden büyük düzenler kurdular\" dedi.",
      "ArabicText": "وَمَكَرُوا۟ مَكْرًۭا كُبَّارًۭا",
      "Number": 22
    },
    {
      "RevelationOrder": 3826,
      "TurkishTranslation": "İnsanlara: \"Sakın tanrılarınızı bırakmayın, Ved, Suva, Yağus, Yeuk ve Nesr putlarından asla vazgeçmeyin\" dediler.",
      "ArabicText": "وَقَالُوا۟ لَا تَذَرُنَّ ءَالِهَتَكُمْ وَلَا تَذَرُنَّ وَدًّۭا وَلَا سُوَاعًۭا وَلَا يَغُوثَ وَيَعُوقَ وَنَسْرًۭا",
      "Number": 23
    },
    {
      "RevelationOrder": 3827,
      "TurkishTranslation": "\"Böylece birçoğunu saptırdılar; Rabbim! Sen bu zalimlerin sadece şaşkınlığını artır.\"",
      "ArabicText": "وَقَدْ أَضَلُّوا۟ كَثِيرًۭا ۖ وَلَا تَزِدِ ٱلظَّٰلِمِينَ إِلَّا ضَلَٰلًۭا",
      "Number": 24
    },
    {
      "RevelationOrder": 3828,
      "TurkishTranslation": "Onlar, günahları yüzünden suda boğuldular; ateşe sokuldular, kendilerine Allah'tan başka yardımcı bulamadılar.",
      "ArabicText": "مِّمَّا خَطِيٓـَٰٔتِهِمْ أُغْرِقُوا۟ فَأُدْخِلُوا۟ نَارًۭا فَلَمْ يَجِدُوا۟ لَهُم مِّن دُونِ ٱللَّهِ أَنصَارًۭا",
      "Number": 25
    },
    {
      "RevelationOrder": 3829,
      "TurkishTranslation": "Nuh dedi ki: \"Rabbim! Yeryüzünde hiçbir inkarcı bırakma.\"",
      "ArabicText": "وَقَالَ نُوحٌۭ رَّبِّ لَا تَذَرْ عَلَى ٱلْأَرْضِ مِنَ ٱلْكَٰفِرِينَ دَيَّارًا",
      "Number": 26
    },
    {
      "RevelationOrder": 3830,
      "TurkishTranslation": "\"Doğrusu Sen onları bırakırsan kullarını saptırırlar; sadece ahlaksız ve çok inkarcıdan başkasını doğurup yetiştirmezler.\"",
      "ArabicText": "إِنَّكَ إِن تَذَرْهُمْ يُضِلُّوا۟ عِبَادَكَ وَلَا يَلِدُوٓا۟ إِلَّا فَاجِرًۭا كَفَّارًۭا",
      "Number": 27
    },
    {
      "RevelationOrder": 3831,
      "TurkishTranslation": "\"Rabbim! Beni, anamı, babamı, evime inanmış olarak gireni, inanan erkek ve kadınları bağışla; zalimlerin de yalnız helakını artır.\"",
      "ArabicText": "رَّبِّ ٱغْفِرْ لِى وَلِوَٰلِدَىَّ وَلِمَن دَخَلَ بَيْتِىَ مُؤْمِنًۭا وَلِلْمُؤْمِنِينَ وَٱلْمُؤْمِنَٰتِ وَلَا تَزِدِ ٱلظَّٰلِمِينَ إِلَّا تَبَارًۢا",
      "Number": 28
    }
  ],
  "SurahName": "سُورَةُ نُوحٍ"
}
